bconsole/__init__.py
bconsole/console.py
bconsole/core.py
bconsole/examples/console.py
bconsole/examples/logger.py
bconsole/extras.py
bconsole/logger.py
bconsole/py.typed
bconsole/utils.py
bconsole-0.0.28.dist-info/LICENSE
bconsole-0.0.28.dist-info/METADATA
bconsole-0.0.28.dist-info/WHEEL
bconsole-0.0.28.dist-info/RECORD
