Metadata-Version: 2.3
Name: bconsole
Version: 0.0.28
Summary: A logging library that provides helper classes and functions to colorize and manipulate terminal output easily.
License: MIT
Keywords: terminal,terminal-colors,logging,logger,colorama
Author: BetaKors
Requires-Python: >=3.13,<4.0
Classifier: Development Status :: 4 - Beta
Classifier: Environment :: Console
Classifier: Intended Audience :: Developers
Classifier: License :: OSI Approved :: MIT License
Classifier: Operating System :: OS Independent
Classifier: Programming Language :: Python
Classifier: Programming Language :: Python :: 3
Classifier: Programming Language :: Python :: 3.13
Classifier: Programming Language :: Python :: 3 :: Only
Classifier: Programming Language :: Python :: Implementation :: CPython
Classifier: Topic :: Terminals
Requires-Dist: colorama (>=0.4.6,<0.5.0)
Requires-Dist: unidecode (>=1.3.6,<2.0.0)
Project-URL: Homepage, https://github.com/betakors/bconsole
Project-URL: Repository, https://github.com/betakors/bconsole
